semanticscholar/__init__.py
semanticscholar/restful.py
semanticscholar/tests.py
pysemanticscholar-0.1.6.dist-info/LICENSE
pysemanticscholar-0.1.6.dist-info/METADATA
pysemanticscholar-0.1.6.dist-info/WHEEL
pysemanticscholar-0.1.6.dist-info/top_level.txt
pysemanticscholar-0.1.6.dist-info/RECORD
