Metadata-Version: 2.1
Name: pysemanticscholar
Version: 0.1.6
Summary: A python library aiming to get data via Semantic Scholar API
Home-page: http://danielnsilva.com/semanticscholar
Author: Daniel Silva
Author-email: danielnsilva@gmail.com
License: MIT
Platform: UNKNOWN
Classifier: Development Status :: 4 - Beta
Classifier: Intended Audience :: Developers
Classifier: Intended Audience :: Science/Research
Classifier: License :: OSI Approved :: MIT License
Classifier: Programming Language :: Python :: 3
Classifier: Topic :: Software Development :: Libraries :: Python Modules
Requires-Dist: requests
Requires-Dist: tenacity
